CTkToolTip/__init__.py
CTkToolTip/ctk_tooltip.py
CTkToolTip-0.7.dist-info/LICENSE
CTkToolTip-0.7.dist-info/METADATA
CTkToolTip-0.7.dist-info/WHEEL
CTkToolTip-0.7.dist-info/top_level.txt
CTkToolTip-0.7.dist-info/RECORD
