Metadata-Version: 2.1
Name: CTkToolTip
Version: 0.7
Summary: Customtkinter Tooltip widget
Home-page: https://github.com/Akascape/CTkToolTip
Author: Akash Bora
License: Creative Commons Zero v1.0 Universal
Keywords: customtkinter,tooltips,popup,widgets,tkinter-widgets,tooltip popup,floating window
Classifier: License :: CC0 1.0 Universal (CC0 1.0) Public Domain Dedication
Classifier: Programming Language :: Python :: 3
Classifier: Operating System :: OS Independent
Requires-Python: >=3.6
License-File: LICENSE
